ready/__init__.py
ready/ready.py
ready/result.py
ready/thttp.py
ready/checks/__init__.py
ready/checks/bad_response.py
ready/checks/content.py
ready/checks/cookies.py
ready/checks/corp_coop_coep.py
ready/checks/csp.py
ready/checks/dns.py
ready/checks/email.py
ready/checks/graphql.py
ready/checks/hsts.py
ready/checks/html.py
ready/checks/leaky_headers.py
ready/checks/ns.py
ready/checks/redirect.py
ready/checks/report_to.py
ready/checks/ssl.py
ready/checks/status.py
ready/checks/swagger.py
ready/checks/well_known.py
ready_check-1.7.0.dist-info/licenses/LICENSE
ready_check-1.7.0.dist-info/METADATA
ready_check-1.7.0.dist-info/WHEEL
ready_check-1.7.0.dist-info/entry_points.txt
ready_check-1.7.0.dist-info/top_level.txt
ready_check-1.7.0.dist-info/RECORD
