Metadata-Version: 2.4
Name: ready-check
Version: 1.7.0
Summary: A developer-friendly web scanning tool
Home-page: https://github.com/sesh/ready
Author: Brenton Cleeland
Author-email: brenton@brntn.me
Project-URL: Bug Tracker, https://github.com/sesh/ready/issues
Classifier: Programming Language :: Python :: 3
Requires-Python: >=3.9
License-File: LICENSE
Requires-Dist: thttp
Requires-Dist: tld
Requires-Dist: beautifulsoup4
Requires-Dist: cryptography
Dynamic: license-file
